assetvaluation/__init__.py
assetvaluation/expenditure.py
assetvaluation/inflation.py
assetvaluation/utils.py
assetvaluation/valuation.py
assetvaluation-0.1.0.dev2.dist-info/LICENSE.txt
assetvaluation-0.1.0.dev2.dist-info/METADATA
assetvaluation-0.1.0.dev2.dist-info/WHEEL
assetvaluation-0.1.0.dev2.dist-info/top_level.txt
assetvaluation-0.1.0.dev2.dist-info/RECORD
