Metadata-Version: 2.1
Name: assetvaluation
Version: 0.1.0.dev2
Summary: Functions to support assets valuation (finance, accounting, and modelling)
Home-page: https://kakila.wemod.info/assetvaluation
Author: Juan Pablo Carbajal
Author-email: ajuanpi+dev@gmail.com
License: UNKNOWN
Project-URL: Source, https://gitlab.wemod.ch/kakila/assetvaluation
Project-URL: Issues, https://gitlab.wemod.ch/kakila/assetvaluation/issues
Platform: UNKNOWN
Classifier: Development Status :: 3 - Alpha
Classifier: Environment :: Other Environment
Classifier: Intended Audience :: Science/Research
Classifier: Intended Audience :: Financial and Insurance Industry
Classifier: Intended Audience :: Other Audience
Classifier: License :: OSI Approved :: GNU General Public License v3 or later (GPLv3+)
Classifier: Operating System :: OS Independent
Classifier: Programming Language :: Python :: 3
Classifier: Topic :: Scientific/Engineering
Classifier: Topic :: Office/Business
Classifier: Topic :: Office/Business :: Financial
Classifier: Topic :: Office/Business :: Financial :: Accounting
Requires-Python: >=3
Requires-Dist: numpy (>=1.17.4)
